MANIFEST.in
README.md
setup.py
pyLruCache/__init__.py
pyLruCache/pyLruCache.py
pyLruCache.egg-info/PKG-INFO
pyLruCache.egg-info/SOURCES.txt
pyLruCache.egg-info/dependency_links.txt
pyLruCache.egg-info/top_level.txt