Metadata-Version: 1.1
Name: pyLruCache
Version: 3.0.1
Summary: Use Lru dict for cache.
Home-page: http://github.com/rfyiamcool
Author: ruifengyun
Author-email: rfyiamcool@163.com
License: MIT
Keywords: lru cache author ruifengyun
Platform: UNKNOWN
Classifier: Topic :: Utilities
Classifier: License :: OSI Approved :: MIT License
